{"cameraMode":{"drawMode":0,"name":"Shaded","section":"Shading Mode"},"sceneLighting":true,"audioPlay":false,"sceneViewState":{"m_AlwaysRefresh":false,"showFog":true,"showSkybox":true,"showFlares":true,"showImageEffects":true,"showParticleSystems":true,"showVisualEffectGraphs":true,"m_FxEnabled":true},"in2DMode":false,"pivot":{"x":78.3057861328125,"y":-34.92399978637695,"z":91.3057861328125},"rotation":{"x":0.16605937480926515,"y":0.33179134130477908,"z":-0.05945299565792084,"w":0.9267141222953796},"size":66.91242218017578,"orthographic":false}